odoo/addons/purchase_create_related/README.rst
odoo/addons/purchase_create_related/__init__.py
odoo/addons/purchase_create_related/__manifest__.py
odoo/addons/purchase_create_related/i18n/es.po
odoo/addons/purchase_create_related/models/__init__.py
odoo/addons/purchase_create_related/models/purchase_order.py
odoo/addons/purchase_create_related/readme/CONTRIBUTORS.md
odoo/addons/purchase_create_related/readme/DESCRIPTION.md
odoo/addons/purchase_create_related/readme/USAGE.md
odoo/addons/purchase_create_related/security/ir.model.access.csv
odoo/addons/purchase_create_related/static/description/icon.png
odoo/addons/purchase_create_related/static/description/index.html
odoo/addons/purchase_create_related/tests/__init__.py
odoo/addons/purchase_create_related/tests/test_purchase_create_related.py
odoo/addons/purchase_create_related/views/purchase_order_views.xml
odoo/addons/purchase_create_related/wizards/__init__.py
odoo/addons/purchase_create_related/wizards/purchase_order_secondary_linker.py
odoo/addons/purchase_create_related/wizards/purchase_order_secondary_linker_views.xml
odoo_addon_purchase_create_related-17.0.1.0.0.1.dist-info/METADATA
odoo_addon_purchase_create_related-17.0.1.0.0.1.dist-info/WHEEL
odoo_addon_purchase_create_related-17.0.1.0.0.1.dist-info/top_level.txt
odoo_addon_purchase_create_related-17.0.1.0.0.1.dist-info/RECORD
